<BackupInst xmlns="http://www.microsoft.com/GroupPolicy/GPOOperations/Manifest"><GPOGuid><![CDATA[{6CBA253A-3CDD-420A-9E04-F1CAF12B88B4}]]></GPOGuid><GPODomain><![CDATA[security.local]]></GPODomain><GPODomainGuid><![CDATA[{1aa99723-c6bc-446c-aa05-83ce7e927986}]]></GPODomainGuid><GPODomainController><![CDATA[DC-SEC-01.security.local]]></GPODomainController><BackupTime><![CDATA[2018-01-22T16:12:43]]></BackupTime><ID><![CDATA[{6AAC5C1E-CF9E-4F09-93E9-258FCB52B41C}]]></ID><Comment><![CDATA[]]></Comment><GPODisplayName><![CDATA[DoD Windows 8 and 8.1 STIG User v1r20]]></GPODisplayName></BackupInst>
